LICENSE
README.md
setup.py
pyonr/__init__.py
pyonr/builtins.py
pyonr/decoder.py
pyonr/encoder.py
pyonr/errors.py
pyonr/pyonr.py
pyonr.egg-info/PKG-INFO
pyonr.egg-info/SOURCES.txt
pyonr.egg-info/dependency_links.txt
pyonr.egg-info/top_level.txt
pyonr/converter/__init__.py