Metadata-Version: 2.1
Name: pyonr
Version: 2.0.0
Summary: PYON Reader - Python Object Nation
Home-page: https://github.com/nawafalqari/pyon/
Author: Nawaf Alqari
Author-email: nawafalqari13@gmail.com
License: MIT
Project-URL: Documentation, https://github.com/nawafalqari/pyon#readme
Project-URL: Bug Tracker, https://github.com/nawafalqari/pyon/issues
Project-URL: Source Code, https://github.com/nawafalqari/pyon/
Project-URL: Discord, https://discord.gg/cpvynqk4XT
Keywords: pyon,pyonr,json,pythonobjectnation,python object nation
Platform: UNKNOWN
Classifier: Programming Language :: Python :: 3
Classifier: License :: OSI Approved :: MIT License
Classifier: Operating System :: OS Independent
License-File: LICENSE
